ladybug_charts/__init__.py
ladybug_charts/_extend_ladybug.py
ladybug_charts/_helper.py
ladybug_charts/_helper_chart.py
ladybug_charts/_psych.py
ladybug_charts/_to_dataframe.py
ladybug_charts/to_figure.py
ladybug_charts/utils.py
ladybug_charts-1.19.4.dist-info/LICENSE
ladybug_charts-1.19.4.dist-info/METADATA
ladybug_charts-1.19.4.dist-info/WHEEL
ladybug_charts-1.19.4.dist-info/top_level.txt
ladybug_charts-1.19.4.dist-info/RECORD
