Metadata-Version: 2.1
Name: ladybug-charts
Version: 1.19.4
Summary: Ladybug extension to generate 2D charts.
Home-page: https://github.com/ladybug-tools/ladybug-charts
Author: Ladybug Tools
Author-email: info@ladybug.tools
License: AGPL-3.0
Platform: UNKNOWN
Classifier: Programming Language :: Python :: 3.7
Classifier: Programming Language :: Python :: Implementation :: CPython
Classifier: License :: OSI Approved :: GNU Affero General Public License v3
Classifier: Operating System :: OS Independent
License-File: LICENSE
Requires-Dist: plotly (>=5.10.0)
Requires-Dist: kaleido
Requires-Dist: lbt-ladybug (>=0.25.146)
Requires-Dist: ladybug-pandas (==0.4.1)
Requires-Dist: numpy (<2.0.0)
